Arky-1.3.1.dist-info/DESCRIPTION.rst
Arky-1.3.1.dist-info/METADATA
Arky-1.3.1.dist-info/RECORD
Arky-1.3.1.dist-info/WHEEL
Arky-1.3.1.dist-info/metadata.json
Arky-1.3.1.dist-info/top_level.txt
arky/__init__.py
arky/cfg.py
arky/ldgr.py
arky/rest.py
arky/slots.py
arky/util.py
arky/ark/__init__.py
arky/ark/aip11.py
arky/ark/crypto.py
arky/ark/aip11/__init__.py
arky/cli/__init__.py
arky/cli/account.py
arky/cli/delegate.py
arky/cli/ledger.py
arky/cli/network.py
arky/lisk/__init__.py
arky/lisk/crypto.py
arky/ndpt/ark.ndpt
arky/ndpt/lsk.ndpt
arky/net/ark-aip11.net
arky/net/ark.net
arky/net/dark.net
arky/net/kapu.net
arky/net/lisk.net
arky/net/oxy.net
arky/net/shift.net
arky/net/tlwf.net
arky/net/toxy.net
arky/net/tshift.net
