Metadata-Version: 2.0
Name: Arky
Version: 1.3.1
Summary: Python API bridging DPOS blockchains
Home-page: https://github.com/ArkEcosystem/arky
Author: Toons
Author-email: moustikitos@gmail.com
License: Copyright 2016-2017 Toons, Copyright 2017 ARK, MIT licence
Download-URL: https://github.com/ArkEcosystem/arky/archive/aip11.zip
Keywords: api,dpos,blockchain
Platform: UNKNOWN
Classifier: Development Status :: 6 - Mature
Classifier: Environment :: Console
Classifier: Environment :: Web Environment
Classifier: Intended Audience :: Developers
Classifier: Intended Audience :: End Users/Desktop
Classifier: License :: OSI Approved :: MIT License
Classifier: Operating System :: OS Independent
Classifier: Programming Language :: Python
Classifier: Programming Language :: Python :: 2
Classifier: Programming Language :: Python :: 3
Requires-Dist: base58
Requires-Dist: docopt
Requires-Dist: ecdsa
Requires-Dist: ledgerblue
Requires-Dist: pynacl
Requires-Dist: pytz
Requires-Dist: requests
